neuroHurst
