Metadata-Version: 2.1
Name: neuroHurst
Version: 0.1.0
Summary: fractal scaling of time series
Home-page: https://github.com/enlberman/hurst_pipeline
Author: andrewstier
Author-email: andrewstier@uchicago.edu
Maintainer: andrewstier
Maintainer-email: andrewstier@uchicago.edu
License: MIT
Platform: OS Independent
Classifier: Environment :: Console
Classifier: Intended Audience :: Science/Research
Classifier: License :: OSI Approved :: MIT License
Classifier: Operating System :: OS Independent
Classifier: Programming Language :: Python
Classifier: Topic :: Scientific/Engineering
Requires-Python: >=2.7,!=3.0.*,!=3.1.*,!=3.2.*,!=3.3.*,!=3.4.*
Provides-Extra: tests
Provides-Extra: travis_tests
Provides-Extra: docs
Provides-Extra: tutorial
Provides-Extra: analysis
Provides-Extra: test
Provides-Extra: doc
